pomatillo/__init__.py
pomatillo-0.0.1.dist-info/LICENSE
pomatillo-0.0.1.dist-info/METADATA
pomatillo-0.0.1.dist-info/WHEEL
pomatillo-0.0.1.dist-info/RECORD
